gtasker/__init__.py
gtasker/cmdparser.py
gtasker/format_printer.py
gtasker/scheduler.py
gtasker/task.py
gtasker/tracker.py
gtasker/utils.py
tests/__init__.py
tests/test_gputracker.py
tests/test_scheduler.py
tests/test_task.py
tests/test_utils.py
gtasker-1.0.1.dist-info/LICENSE.txt
gtasker-1.0.1.dist-info/METADATA
gtasker-1.0.1.dist-info/WHEEL
gtasker-1.0.1.dist-info/entry_points.txt
gtasker-1.0.1.dist-info/top_level.txt
gtasker-1.0.1.dist-info/RECORD
