Metadata-Version: 2.1
Name: gtasker
Version: 1.0.1
Summary: Demo Package for GTasker.
Home-page: https://github.com/Suffoquer-fang/GTasker
Author: Suffoquer
Author-email: 1161290791@qq.com
License: MIT
Keywords: gpu tasker
Classifier: Programming Language :: Python :: 3
Classifier: License :: OSI Approved :: MIT License
Classifier: Operating System :: OS Independent
License-File: LICENSE.txt
Requires-Dist: jsonrpclib (==0.2.1)
Requires-Dist: gpustat (==0.6.0)
Requires-Dist: appdirs (==1.4.4)
Requires-Dist: psutil (==5.9.0)
Requires-Dist: rich (==12.4.1)
